{
  "version": 1.0,
  "grid_size": 128,
  "tabs": [
    {
      "name": "Teleoperated",
      "grid_layout": {
        "layouts": [
          {
            "title": "Sensors",
            "x": 1664.0,
            "y": 0.0,
            "width": 256.0,
            "height": 896.0,
            "type": "List Layout",
            "properties": {
              "label_position": "TOP"
            },
            "children": [
              {
                "title": "Pitch",
                "x": 0.0,
                "y": 0.0,
                "width": 128.0,
                "height": 128.0,
                "type": "Text Display",
                "properties": {
                  "topic": "/Sensors/Pitch",
                  "period": 0.06,
                  "data_type": "double",
                  "show_submit_button": false
                }
              },
              {
                "title": "PitchDot",
                "x": 0.0,
                "y": 0.0,
                "width": 128.0,
                "height": 128.0,
                "type": "Text Display",
                "properties": {
                  "topic": "/Sensors/PitchDot",
                  "period": 0.06,
                  "data_type": "double",
                  "show_submit_button": false
                }
              },
              {
                "title": "Roll",
                "x": 0.0,
                "y": 0.0,
                "width": 128.0,
                "height": 128.0,
                "type": "Text Display",
                "properties": {
                  "topic": "/Sensors/Roll",
                  "period": 0.06,
                  "data_type": "double",
                  "show_submit_button": false
                }
              },
              {
                "title": "RollDot",
                "x": 0.0,
                "y": 0.0,
                "width": 128.0,
                "height": 128.0,
                "type": "Text Display",
                "properties": {
                  "topic": "/Sensors/RollDot",
                  "period": 0.06,
                  "data_type": "double",
                  "show_submit_button": false
                }
              },
              {
                "title": "Rotation",
                "x": 0.0,
                "y": 0.0,
                "width": 128.0,
                "height": 128.0,
                "type": "Text Display",
                "properties": {
                  "topic": "/Sensors/Rotation",
                  "period": 0.06,
                  "data_type": "double",
                  "show_submit_button": false
                }
              },
              {
                "title": "Yaw",
                "x": 0.0,
                "y": 0.0,
                "width": 128.0,
                "height": 128.0,
                "type": "Text Display",
                "properties": {
                  "topic": "/Sensors/Yaw",
                  "period": 0.06,
                  "data_type": "double",
                  "show_submit_button": false
                }
              },
              {
                "title": "YawDot",
                "x": 0.0,
                "y": 0.0,
                "width": 128.0,
                "height": 128.0,
                "type": "Text Display",
                "properties": {
                  "topic": "/Sensors/YawDot",
                  "period": 0.06,
                  "data_type": "double",
                  "show_submit_button": false
                }
              },
              {
                "title": "yawOffset",
                "x": 0.0,
                "y": 0.0,
                "width": 128.0,
                "height": 128.0,
                "type": "Text Display",
                "properties": {
                  "topic": "/Sensors/yawOffset",
                  "period": 0.06,
                  "data_type": "double",
                  "show_submit_button": false
                }
              },
              {
                "title": "yawSimpleDBG",
                "x": 0.0,
                "y": 0.0,
                "width": 128.0,
                "height": 128.0,
                "type": "Text Display",
                "properties": {
                  "topic": "/Sensors/yawSimpleDBG",
                  "period": 0.06,
                  "data_type": "double",
                  "show_submit_button": false
                }
              },
              {
                "title": "yawZquatDBG",
                "x": 0.0,
                "y": 0.0,
                "width": 128.0,
                "height": 128.0,
                "type": "Text Display",
                "properties": {
                  "topic": "/Sensors/yawZquatDBG",
                  "period": 0.06,
                  "data_type": "double",
                  "show_submit_button": false
                }
              },
              {
                "title": "CanRxError",
                "x": 0.0,
                "y": 0.0,
                "width": 128.0,
                "height": 128.0,
                "type": "Text Display",
                "properties": {
                  "topic": "/Sensors/CanRxError",
                  "period": 0.06,
                  "data_type": "double",
                  "show_submit_button": false
                }
              }
            ]
          },
          {
            "title": "limelight",
            "x": 1408.0,
            "y": 0.0,
            "width": 256.0,
            "height": 384.0,
            "type": "List Layout",
            "properties": {
              "label_position": "TOP"
            },
            "children": [
              {
                "title": "booleanLeds",
                "x": 0.0,
                "y": 0.0,
                "width": 128.0,
                "height": 128.0,
                "type": "Boolean Box",
                "properties": {
                  "topic": "/limelight/booleanLeds",
                  "period": 0.06,
                  "data_type": "boolean",
                  "true_color": 4283215696,
                  "false_color": 4294198070,
                  "true_icon": "None",
                  "false_icon": "None"
                }
              },
              {
                "title": "camerapose_robotspace_set",
                "x": 0.0,
                "y": 0.0,
                "width": 128.0,
                "height": 128.0,
                "type": "Text Display",
                "properties": {
                  "topic": "/limelight/camerapose_robotspace_set",
                  "period": 0.06,
                  "data_type": "double[]",
                  "show_submit_button": false
                }
              },
              {
                "title": "ledMode",
                "x": 0.0,
                "y": 0.0,
                "width": 128.0,
                "height": 128.0,
                "type": "Text Display",
                "properties": {
                  "topic": "/limelight/ledMode",
                  "period": 0.06,
                  "data_type": "double",
                  "show_submit_button": false
                }
              },
              {
                "title": "robot_orientation_set",
                "x": 0.0,
                "y": 0.0,
                "width": 128.0,
                "height": 128.0,
                "type": "Text Display",
                "properties": {
                  "topic": "/limelight/robot_orientation_set",
                  "period": 0.06,
                  "data_type": "double[]",
                  "show_submit_button": false
                }
              }
            ]
          },
          {
            "title": "Odometry_Robot_01",
            "x": 1152.0,
            "y": 256.0,
            "width": 256.0,
            "height": 256.0,
            "type": "List Layout",
            "properties": {
              "label_position": "TOP"
            },
            "children": [
              {
                "title": "Robot_01_h",
                "x": 0.0,
                "y": 0.0,
                "width": 128.0,
                "height": 128.0,
                "type": "Text Display",
                "properties": {
                  "topic": "/Odometry_Robot_01/Robot_01_h",
                  "period": 0.06,
                  "data_type": "double",
                  "show_submit_button": false
                }
              },
              {
                "title": "Robot_01_x",
                "x": 0.0,
                "y": 0.0,
                "width": 128.0,
                "height": 128.0,
                "type": "Text Display",
                "properties": {
                  "topic": "/Odometry_Robot_01/Robot_01_x",
                  "period": 0.06,
                  "data_type": "double",
                  "show_submit_button": false
                }
              },
              {
                "title": "Robot_01_y",
                "x": 0.0,
                "y": 0.0,
                "width": 128.0,
                "height": 128.0,
                "type": "Text Display",
                "properties": {
                  "topic": "/Odometry_Robot_01/Robot_01_y",
                  "period": 0.06,
                  "data_type": "double",
                  "show_submit_button": false
                }
              }
            ]
          },
          {
            "title": "compareLLOdo",
            "x": 1152.0,
            "y": 0.0,
            "width": 256.0,
            "height": 256.0,
            "type": "List Layout",
            "properties": {
              "label_position": "LEFT"
            },
            "children": [
              {
                "title": "diffHeading",
                "x": 0.0,
                "y": 0.0,
                "width": 128.0,
                "height": 128.0,
                "type": "Text Display",
                "properties": {
                  "topic": "/VisionPoseEstimator//compareLLOdo/diffHeading",
                  "period": 0.06,
                  "data_type": "double",
                  "show_submit_button": false
                }
              },
              {
                "title": "diffX",
                "x": 0.0,
                "y": 0.0,
                "width": 128.0,
                "height": 128.0,
                "type": "Text Display",
                "properties": {
                  "topic": "/VisionPoseEstimator//compareLLOdo/diffX",
                  "period": 0.06,
                  "data_type": "double",
                  "show_submit_button": false
                }
              },
              {
                "title": "diffY",
                "x": 0.0,
                "y": 0.0,
                "width": 128.0,
                "height": 128.0,
                "type": "Text Display",
                "properties": {
                  "topic": "/VisionPoseEstimator//compareLLOdo/diffY",
                  "period": 0.06,
                  "data_type": "double",
                  "show_submit_button": false
                }
              }
            ]
          },
          {
            "title": "MK3-BackLeft",
            "x": 768.0,
            "y": 512.0,
            "width": 256.0,
            "height": 768.0,
            "type": "List Layout",
            "properties": {
              "label_position": "TOP"
            },
            "children": [
              {
                "title": "angle",
                "x": 0.0,
                "y": 0.0,
                "width": 128.0,
                "height": 128.0,
                "type": "Text Display",
                "properties": {
                  "topic": "/DriveModules//MK3-BackLeft/angle",
                  "period": 0.06,
                  "data_type": "double",
                  "show_submit_button": false
                }
              },
              {
                "title": "angleMod",
                "x": 0.0,
                "y": 0.0,
                "width": 128.0,
                "height": 128.0,
                "type": "Text Display",
                "properties": {
                  "topic": "/DriveModules//MK3-BackLeft/angleMod",
                  "period": 0.06,
                  "data_type": "double",
                  "show_submit_button": false
                }
              },
              {
                "title": "angle_ext",
                "x": 0.0,
                "y": 0.0,
                "width": 128.0,
                "height": 128.0,
                "type": "Text Display",
                "properties": {
                  "topic": "/DriveModules//MK3-BackLeft/angle_ext",
                  "period": 0.06,
                  "data_type": "double",
                  "show_submit_button": false
                }
              },
              {
                "title": "angle_target",
                "x": 0.0,
                "y": 0.0,
                "width": 128.0,
                "height": 128.0,
                "type": "Text Display",
                "properties": {
                  "topic": "/DriveModules//MK3-BackLeft/angle_target",
                  "period": 0.06,
                  "data_type": "double",
                  "show_submit_button": false
                }
              },
              {
                "title": "applied_output",
                "x": 0.0,
                "y": 0.0,
                "width": 128.0,
                "height": 128.0,
                "type": "Text Display",
                "properties": {
                  "topic": "/DriveModules//MK3-BackLeft/applied_output",
                  "period": 0.06,
                  "data_type": "double",
                  "show_submit_button": false
                }
              },
              {
                "title": "motor_current",
                "x": 0.0,
                "y": 0.0,
                "width": 128.0,
                "height": 128.0,
                "type": "Text Display",
                "properties": {
                  "topic": "/DriveModules//MK3-BackLeft/motor_current",
                  "period": 0.06,
                  "data_type": "double",
                  "show_submit_button": false
                }
              },
              {
                "title": "position",
                "x": 0.0,
                "y": 0.0,
                "width": 128.0,
                "height": 128.0,
                "type": "Text Display",
                "properties": {
                  "topic": "/DriveModules//MK3-BackLeft/position",
                  "period": 0.06,
                  "data_type": "double",
                  "show_submit_button": false
                }
              },
              {
                "title": "velocity",
                "x": 0.0,
                "y": 0.0,
                "width": 128.0,
                "height": 128.0,
                "type": "Text Display",
                "properties": {
                  "topic": "/DriveModules//MK3-BackLeft/velocity",
                  "period": 0.06,
                  "data_type": "double",
                  "show_submit_button": false
                }
              },
              {
                "title": "velocity_target",
                "x": 0.0,
                "y": 0.0,
                "width": 128.0,
                "height": 128.0,
                "type": "Text Display",
                "properties": {
                  "topic": "/DriveModules//MK3-BackLeft/velocity_target",
                  "period": 0.06,
                  "data_type": "double",
                  "show_submit_button": false
                }
              }
            ]
          },
          {
            "title": "MK3-BackRight",
            "x": 512.0,
            "y": 512.0,
            "width": 256.0,
            "height": 768.0,
            "type": "List Layout",
            "properties": {
              "label_position": "TOP"
            },
            "children": [
              {
                "title": "angle",
                "x": 0.0,
                "y": 0.0,
                "width": 128.0,
                "height": 128.0,
                "type": "Text Display",
                "properties": {
                  "topic": "/DriveModules//MK3-BackRight/angle",
                  "period": 0.06,
                  "data_type": "double",
                  "show_submit_button": false
                }
              },
              {
                "title": "angleMod",
                "x": 0.0,
                "y": 0.0,
                "width": 128.0,
                "height": 128.0,
                "type": "Text Display",
                "properties": {
                  "topic": "/DriveModules//MK3-BackRight/angleMod",
                  "period": 0.06,
                  "data_type": "double",
                  "show_submit_button": false
                }
              },
              {
                "title": "angle_ext",
                "x": 0.0,
                "y": 0.0,
                "width": 128.0,
                "height": 128.0,
                "type": "Text Display",
                "properties": {
                  "topic": "/DriveModules//MK3-BackRight/angle_ext",
                  "period": 0.06,
                  "data_type": "double",
                  "show_submit_button": false
                }
              },
              {
                "title": "angle_target",
                "x": 0.0,
                "y": 0.0,
                "width": 128.0,
                "height": 128.0,
                "type": "Text Display",
                "properties": {
                  "topic": "/DriveModules//MK3-BackRight/angle_target",
                  "period": 0.06,
                  "data_type": "double",
                  "show_submit_button": false
                }
              },
              {
                "title": "applied_output",
                "x": 0.0,
                "y": 0.0,
                "width": 128.0,
                "height": 128.0,
                "type": "Text Display",
                "properties": {
                  "topic": "/DriveModules//MK3-BackRight/applied_output",
                  "period": 0.06,
                  "data_type": "double",
                  "show_submit_button": false
                }
              },
              {
                "title": "motor_current",
                "x": 0.0,
                "y": 0.0,
                "width": 128.0,
                "height": 128.0,
                "type": "Text Display",
                "properties": {
                  "topic": "/DriveModules//MK3-BackRight/motor_current",
                  "period": 0.06,
                  "data_type": "double",
                  "show_submit_button": false
                }
              },
              {
                "title": "position",
                "x": 0.0,
                "y": 0.0,
                "width": 128.0,
                "height": 128.0,
                "type": "Text Display",
                "properties": {
                  "topic": "/DriveModules//MK3-BackRight/position",
                  "period": 0.06,
                  "data_type": "double",
                  "show_submit_button": false
                }
              },
              {
                "title": "velocity",
                "x": 0.0,
                "y": 0.0,
                "width": 128.0,
                "height": 128.0,
                "type": "Text Display",
                "properties": {
                  "topic": "/DriveModules//MK3-BackRight/velocity",
                  "period": 0.06,
                  "data_type": "double",
                  "show_submit_button": false
                }
              },
              {
                "title": "velocity_target",
                "x": 0.0,
                "y": 0.0,
                "width": 128.0,
                "height": 128.0,
                "type": "Text Display",
                "properties": {
                  "topic": "/DriveModules//MK3-BackRight/velocity_target",
                  "period": 0.06,
                  "data_type": "double",
                  "show_submit_button": false
                }
              }
            ]
          },
          {
            "title": "MK3-FrontLeft",
            "x": 512.0,
            "y": 128.0,
            "width": 256.0,
            "height": 384.0,
            "type": "List Layout",
            "properties": {
              "label_position": "TOP"
            },
            "children": [
              {
                "title": "angle",
                "x": 0.0,
                "y": 0.0,
                "width": 128.0,
                "height": 128.0,
                "type": "Text Display",
                "properties": {
                  "topic": "/DriveModules//MK3-FrontLeft/angle",
                  "period": 0.06,
                  "data_type": "double",
                  "show_submit_button": false
                }
              },
              {
                "title": "angleMod",
                "x": 0.0,
                "y": 0.0,
                "width": 128.0,
                "height": 128.0,
                "type": "Text Display",
                "properties": {
                  "topic": "/DriveModules//MK3-FrontLeft/angleMod",
                  "period": 0.06,
                  "data_type": "double",
                  "show_submit_button": false
                }
              },
              {
                "title": "angle_ext",
                "x": 0.0,
                "y": 0.0,
                "width": 128.0,
                "height": 128.0,
                "type": "Text Display",
                "properties": {
                  "topic": "/DriveModules//MK3-FrontLeft/angle_ext",
                  "period": 0.06,
                  "data_type": "double",
                  "show_submit_button": false
                }
              },
              {
                "title": "angle_target",
                "x": 0.0,
                "y": 0.0,
                "width": 128.0,
                "height": 128.0,
                "type": "Text Display",
                "properties": {
                  "topic": "/DriveModules//MK3-FrontLeft/angle_target",
                  "period": 0.06,
                  "data_type": "double",
                  "show_submit_button": false
                }
              },
              {
                "title": "applied_output",
                "x": 0.0,
                "y": 0.0,
                "width": 128.0,
                "height": 128.0,
                "type": "Text Display",
                "properties": {
                  "topic": "/DriveModules//MK3-FrontLeft/applied_output",
                  "period": 0.06,
                  "data_type": "double",
                  "show_submit_button": false
                }
              },
              {
                "title": "motor_current",
                "x": 0.0,
                "y": 0.0,
                "width": 128.0,
                "height": 128.0,
                "type": "Text Display",
                "properties": {
                  "topic": "/DriveModules//MK3-FrontLeft/motor_current",
                  "period": 0.06,
                  "data_type": "double",
                  "show_submit_button": false
                }
              },
              {
                "title": "position",
                "x": 0.0,
                "y": 0.0,
                "width": 128.0,
                "height": 128.0,
                "type": "Text Display",
                "properties": {
                  "topic": "/DriveModules//MK3-FrontLeft/position",
                  "period": 0.06,
                  "data_type": "double",
                  "show_submit_button": false
                }
              },
              {
                "title": "velocity",
                "x": 0.0,
                "y": 0.0,
                "width": 128.0,
                "height": 128.0,
                "type": "Text Display",
                "properties": {
                  "topic": "/DriveModules//MK3-FrontLeft/velocity",
                  "period": 0.06,
                  "data_type": "double",
                  "show_submit_button": false
                }
              },
              {
                "title": "velocity_target",
                "x": 0.0,
                "y": 0.0,
                "width": 128.0,
                "height": 128.0,
                "type": "Text Display",
                "properties": {
                  "topic": "/DriveModules//MK3-FrontLeft/velocity_target",
                  "period": 0.06,
                  "data_type": "double",
                  "show_submit_button": false
                }
              }
            ]
          },
          {
            "title": "MK3-FrontRight",
            "x": 768.0,
            "y": 128.0,
            "width": 256.0,
            "height": 384.0,
            "type": "List Layout",
            "properties": {
              "label_position": "TOP"
            },
            "children": [
              {
                "title": "angle",
                "x": 0.0,
                "y": 0.0,
                "width": 128.0,
                "height": 128.0,
                "type": "Text Display",
                "properties": {
                  "topic": "/DriveModules//MK3-FrontRight/angle",
                  "period": 0.06,
                  "data_type": "double",
                  "show_submit_button": false
                }
              },
              {
                "title": "angleMod",
                "x": 0.0,
                "y": 0.0,
                "width": 128.0,
                "height": 128.0,
                "type": "Text Display",
                "properties": {
                  "topic": "/DriveModules//MK3-FrontRight/angleMod",
                  "period": 0.06,
                  "data_type": "double",
                  "show_submit_button": false
                }
              },
              {
                "title": "angle_ext",
                "x": 0.0,
                "y": 0.0,
                "width": 128.0,
                "height": 128.0,
                "type": "Text Display",
                "properties": {
                  "topic": "/DriveModules//MK3-FrontRight/angle_ext",
                  "period": 0.06,
                  "data_type": "double",
                  "show_submit_button": false
                }
              },
              {
                "title": "angle_target",
                "x": 0.0,
                "y": 0.0,
                "width": 128.0,
                "height": 128.0,
                "type": "Text Display",
                "properties": {
                  "topic": "/DriveModules//MK3-FrontRight/angle_target",
                  "period": 0.06,
                  "data_type": "double",
                  "show_submit_button": false
                }
              },
              {
                "title": "applied_output",
                "x": 0.0,
                "y": 0.0,
                "width": 128.0,
                "height": 128.0,
                "type": "Text Display",
                "properties": {
                  "topic": "/DriveModules//MK3-FrontRight/applied_output",
                  "period": 0.06,
                  "data_type": "double",
                  "show_submit_button": false
                }
              },
              {
                "title": "motor_current",
                "x": 0.0,
                "y": 0.0,
                "width": 128.0,
                "height": 128.0,
                "type": "Text Display",
                "properties": {
                  "topic": "/DriveModules//MK3-FrontRight/motor_current",
                  "period": 0.06,
                  "data_type": "double",
                  "show_submit_button": false
                }
              },
              {
                "title": "position",
                "x": 0.0,
                "y": 0.0,
                "width": 128.0,
                "height": 128.0,
                "type": "Text Display",
                "properties": {
                  "topic": "/DriveModules//MK3-FrontRight/position",
                  "period": 0.06,
                  "data_type": "double",
                  "show_submit_button": false
                }
              },
              {
                "title": "velocity",
                "x": 0.0,
                "y": 0.0,
                "width": 128.0,
                "height": 128.0,
                "type": "Text Display",
                "properties": {
                  "topic": "/DriveModules//MK3-FrontRight/velocity",
                  "period": 0.06,
                  "data_type": "double",
                  "show_submit_button": false
                }
              },
              {
                "title": "velocity_target",
                "x": 0.0,
                "y": 0.0,
                "width": 128.0,
                "height": 128.0,
                "type": "Text Display",
                "properties": {
                  "topic": "/DriveModules//MK3-FrontRight/velocity_target",
                  "period": 0.06,
                  "data_type": "double",
                  "show_submit_button": false
                }
              }
            ]
          },
          {
            "title": "SwerveDrivetrain",
            "x": 256.0,
            "y": 128.0,
            "width": 128.0,
            "height": 256.0,
            "type": "List Layout",
            "properties": {
              "label_position": "LEFT"
            },
            "children": [
              {
                "title": "Vrot",
                "x": 0.0,
                "y": 0.0,
                "width": 128.0,
                "height": 128.0,
                "type": "Text Display",
                "properties": {
                  "topic": "/SwerveDrivetrain/Vrot",
                  "period": 0.033,
                  "data_type": "double",
                  "show_submit_button": false
                }
              },
              {
                "title": "Vx ",
                "x": 0.0,
                "y": 0.0,
                "width": 128.0,
                "height": 128.0,
                "type": "Text Display",
                "properties": {
                  "topic": "/SwerveDrivetrain/Vx ",
                  "period": 0.06,
                  "data_type": "double",
                  "show_submit_button": false
                }
              },
              {
                "title": "Vy ",
                "x": 0.0,
                "y": 0.0,
                "width": 128.0,
                "height": 128.0,
                "type": "Text Display",
                "properties": {
                  "topic": "/SwerveDrivetrain/Vy ",
                  "period": 0.06,
                  "data_type": "double",
                  "show_submit_button": false
                }
              }
            ]
          },
          {
            "title": "Elevator_Subsystem",
            "x": 1920.0,
            "y": 0.0,
            "width": 256.0,
            "height": 768.0,
            "type": "List Layout",
            "properties": {
              "label_position": "TOP"
            },
            "children": [
              {
                "title": "atSetpoint",
                "x": 0.0,
                "y": 0.0,
                "width": 128.0,
                "height": 128.0,
                "type": "Boolean Box",
                "properties": {
                  "topic": "/Elevator_Subsystem/atSetpoint",
                  "period": 0.06,
                  "data_type": "boolean",
                  "true_color": 4283215696,
                  "false_color": 4294198070,
                  "true_icon": "None",
                  "false_icon": "None"
                }
              },
              {
                "title": "cmdVel",
                "x": 0.0,
                "y": 0.0,
                "width": 128.0,
                "height": 128.0,
                "type": "Text Display",
                "properties": {
                  "topic": "/Elevator_Subsystem/cmdVel",
                  "period": 0.06,
                  "data_type": "double",
                  "show_submit_button": false
                }
              },
              {
                "title": "currentHeight",
                "x": 0.0,
                "y": 0.0,
                "width": 128.0,
                "height": 128.0,
                "type": "Text Display",
                "properties": {
                  "topic": "/Elevator_Subsystem/currentHeight",
                  "period": 0.06,
                  "data_type": "double",
                  "show_submit_button": false
                }
              },
              {
                "title": "desiredHeight",
                "x": 0.0,
                "y": 0.0,
                "width": 128.0,
                "height": 128.0,
                "type": "Text Display",
                "properties": {
                  "topic": "/Elevator_Subsystem/desiredHeight",
                  "period": 0.06,
                  "data_type": "double",
                  "show_submit_button": false
                }
              },
              {
                "title": "followCurrent",
                "x": 0.0,
                "y": 0.0,
                "width": 128.0,
                "height": 128.0,
                "type": "Text Display",
                "properties": {
                  "topic": "/Elevator_Subsystem/followCurrent",
                  "period": 0.06,
                  "data_type": "double",
                  "show_submit_button": false
                }
              },
              {
                "title": "iAccum",
                "x": 0.0,
                "y": 0.0,
                "width": 128.0,
                "height": 128.0,
                "type": "Text Display",
                "properties": {
                  "topic": "/Elevator_Subsystem/iAccum",
                  "period": 0.06,
                  "data_type": "double",
                  "show_submit_button": false
                }
              },
              {
                "title": "mainCurrent",
                "x": 0.0,
                "y": 0.0,
                "width": 128.0,
                "height": 128.0,
                "type": "Text Display",
                "properties": {
                  "topic": "/Elevator_Subsystem/mainCurrent",
                  "period": 0.06,
                  "data_type": "double",
                  "show_submit_button": false
                }
              },
              {
                "title": "measVel",
                "x": 0.0,
                "y": 0.0,
                "width": 128.0,
                "height": 128.0,
                "type": "Text Display",
                "properties": {
                  "topic": "/Elevator_Subsystem/measVel",
                  "period": 0.06,
                  "data_type": "double",
                  "show_submit_button": false
                }
              },
              {
                "title": "zeroLimitSwitch",
                "x": 0.0,
                "y": 0.0,
                "width": 128.0,
                "height": 128.0,
                "type": "Boolean Box",
                "properties": {
                  "topic": "/Elevator_Subsystem/zeroLimitSwitch",
                  "period": 0.06,
                  "data_type": "boolean",
                  "true_color": 4283215696,
                  "false_color": 4294198070,
                  "true_icon": "None",
                  "false_icon": "None"
                }
              }
            ]
          },
          {
            "title": "EndEffector_Subsystem",
            "x": 2176.0,
            "y": 0.0,
            "width": 256.0,
            "height": 640.0,
            "type": "List Layout",
            "properties": {
              "label_position": "TOP"
            },
            "children": [
              {
                "title": "cmdPCT",
                "x": 0.0,
                "y": 0.0,
                "width": 128.0,
                "height": 128.0,
                "type": "Text Display",
                "properties": {
                  "topic": "/EndEffector_Subsystem/cmdPCT",
                  "period": 0.06,
                  "data_type": "double",
                  "show_submit_button": false
                }
              },
              {
                "title": "cmdRPM",
                "x": 0.0,
                "y": 0.0,
                "width": 128.0,
                "height": 128.0,
                "type": "Text Display",
                "properties": {
                  "topic": "/EndEffector_Subsystem/cmdRPM",
                  "period": 0.06,
                  "data_type": "double",
                  "show_submit_button": false
                }
              },
              {
                "title": "hasPiece",
                "x": 0.0,
                "y": 0.0,
                "width": 128.0,
                "height": 128.0,
                "type": "Boolean Box",
                "properties": {
                  "topic": "/EndEffector_Subsystem/hasPiece",
                  "period": 0.06,
                  "data_type": "boolean",
                  "true_color": 4283215696,
                  "false_color": 4294198070,
                  "true_icon": "None",
                  "false_icon": "None"
                }
              },
              {
                "title": "measPCT",
                "x": 0.0,
                "y": 0.0,
                "width": 128.0,
                "height": 128.0,
                "type": "Text Display",
                "properties": {
                  "topic": "/EndEffector_Subsystem/measPCT",
                  "period": 0.06,
                  "data_type": "double",
                  "show_submit_button": false
                }
              },
              {
                "title": "measRPM",
                "x": 0.0,
                "y": 0.0,
                "width": 128.0,
                "height": 128.0,
                "type": "Text Display",
                "properties": {
                  "topic": "/EndEffector_Subsystem/measRPM",
                  "period": 0.06,
                  "data_type": "double",
                  "show_submit_button": false
                }
              },
              {
                "title": "pieceReady",
                "x": 0.0,
                "y": 0.0,
                "width": 128.0,
                "height": 128.0,
                "type": "Boolean Box",
                "properties": {
                  "topic": "/EndEffector_Subsystem/pieceReady",
                  "period": 0.06,
                  "data_type": "boolean",
                  "true_color": 4283215696,
                  "false_color": 4294198070,
                  "true_icon": "None",
                  "false_icon": "None"
                }
              }
            ]
          },
          {
            "title": "Ground Intake",
            "x": 2176.0,
            "y": 640.0,
            "width": 256.0,
            "height": 640.0,
            "type": "List Layout",
            "properties": {
              "label_position": "TOP"
            },
            "children": [
              {
                "title": "bottom cmd position",
                "x": 0.0,
                "y": 0.0,
                "width": 128.0,
                "height": 128.0,
                "type": "Text Display",
                "properties": {
                  "topic": "/Ground Intake/bottom cmd position",
                  "period": 0.06,
                  "data_type": "double",
                  "show_submit_button": false
                }
              },
              {
                "title": "bottom cmd velocity",
                "x": 0.0,
                "y": 0.0,
                "width": 128.0,
                "height": 128.0,
                "type": "Text Display",
                "properties": {
                  "topic": "/Ground Intake/bottom cmd velocity",
                  "period": 0.06,
                  "data_type": "double",
                  "show_submit_button": false
                }
              },
              {
                "title": "bottom position",
                "x": 0.0,
                "y": 0.0,
                "width": 128.0,
                "height": 128.0,
                "type": "Text Display",
                "properties": {
                  "topic": "/Ground Intake/bottom position",
                  "period": 0.06,
                  "data_type": "double",
                  "show_submit_button": false
                }
              },
              {
                "title": "bottom velocity",
                "x": 0.0,
                "y": 0.0,
                "width": 128.0,
                "height": 128.0,
                "type": "Text Display",
                "properties": {
                  "topic": "/Ground Intake/bottom velocity",
                  "period": 0.06,
                  "data_type": "double",
                  "show_submit_button": false
                }
              },
              {
                "title": "hasAlgae",
                "x": 0.0,
                "y": 0.0,
                "width": 128.0,
                "height": 128.0,
                "type": "Boolean Box",
                "properties": {
                  "topic": "/Ground Intake/hasAlgae",
                  "period": 0.06,
                  "data_type": "boolean",
                  "true_color": 4283215696,
                  "false_color": 4294198070,
                  "true_icon": "None",
                  "false_icon": "None"
                }
              },
              {
                "title": "hasCoral",
                "x": 0.0,
                "y": 0.0,
                "width": 128.0,
                "height": 128.0,
                "type": "Boolean Box",
                "properties": {
                  "topic": "/Ground Intake/hasCoral",
                  "period": 0.06,
                  "data_type": "boolean",
                  "true_color": 4283215696,
                  "false_color": 4294198070,
                  "true_icon": "None",
                  "false_icon": "None"
                }
              },
              {
                "title": "is top at setpoint",
                "x": 0.0,
                "y": 0.0,
                "width": 128.0,
                "height": 128.0,
                "type": "Boolean Box",
                "properties": {
                  "topic": "/Ground Intake/is top at setpoint",
                  "period": 0.06,
                  "data_type": "boolean",
                  "true_color": 4283215696,
                  "false_color": 4294198070,
                  "true_icon": "None",
                  "false_icon": "None"
                }
              },
              {
                "title": "roller velocity",
                "x": 0.0,
                "y": 0.0,
                "width": 128.0,
                "height": 128.0,
                "type": "Text Display",
                "properties": {
                  "topic": "/Ground Intake/roller velocity",
                  "period": 0.06,
                  "data_type": "double",
                  "show_submit_button": false
                }
              },
              {
                "title": "top IAccum",
                "x": 0.0,
                "y": 0.0,
                "width": 128.0,
                "height": 128.0,
                "type": "Text Display",
                "properties": {
                  "topic": "/Ground Intake/top IAccum",
                  "period": 0.06,
                  "data_type": "double",
                  "show_submit_button": false
                }
              },
              {
                "title": "top cmd position",
                "x": 0.0,
                "y": 0.0,
                "width": 128.0,
                "height": 128.0,
                "type": "Text Display",
                "properties": {
                  "topic": "/Ground Intake/top cmd position",
                  "period": 0.06,
                  "data_type": "double",
                  "show_submit_button": false
                }
              },
              {
                "title": "top cmd velocity",
                "x": 0.0,
                "y": 0.0,
                "width": 128.0,
                "height": 128.0,
                "type": "Text Display",
                "properties": {
                  "topic": "/Ground Intake/top cmd velocity",
                  "period": 0.06,
                  "data_type": "double",
                  "show_submit_button": false
                }
              },
              {
                "title": "top position",
                "x": 0.0,
                "y": 0.0,
                "width": 128.0,
                "height": 128.0,
                "type": "Text Display",
                "properties": {
                  "topic": "/Ground Intake/top position",
                  "period": 0.06,
                  "data_type": "double",
                  "show_submit_button": false
                }
              },
              {
                "title": "top velocity",
                "x": 0.0,
                "y": 0.0,
                "width": 128.0,
                "height": 128.0,
                "type": "Text Display",
                "properties": {
                  "topic": "/Ground Intake/top velocity",
                  "period": 0.06,
                  "data_type": "double",
                  "show_submit_button": false
                }
              }
            ]
          },
          {
            "title": "Limelight-Out",
            "x": 1408.0,
            "y": 384.0,
            "width": 256.0,
            "height": 768.0,
            "type": "List Layout",
            "properties": {
              "label_position": "TOP"
            },
            "children": [
              {
                "title": "LL Blue Pose X",
                "x": 0.0,
                "y": 0.0,
                "width": 128.0,
                "height": 128.0,
                "type": "Text Display",
                "properties": {
                  "topic": "/limelight/out//LL Blue Pose X",
                  "period": 0.06,
                  "data_type": "double",
                  "show_submit_button": false
                }
              },
              {
                "title": "LL Blue Pose Y",
                "x": 0.0,
                "y": 0.0,
                "width": 128.0,
                "height": 128.0,
                "type": "Text Display",
                "properties": {
                  "topic": "/limelight/out//LL Blue Pose Y",
                  "period": 0.06,
                  "data_type": "double",
                  "show_submit_button": false
                }
              },
              {
                "title": "LL Blue Pose2 X",
                "x": 0.0,
                "y": 0.0,
                "width": 128.0,
                "height": 128.0,
                "type": "Text Display",
                "properties": {
                  "topic": "/limelight/out//LL Blue Pose2 X",
                  "period": 0.06,
                  "data_type": "double",
                  "show_submit_button": false
                }
              },
              {
                "title": "LL Blue Pose2 Y",
                "x": 0.0,
                "y": 0.0,
                "width": 128.0,
                "height": 128.0,
                "type": "Text Display",
                "properties": {
                  "topic": "/limelight/out//LL Blue Pose2 Y",
                  "period": 0.06,
                  "data_type": "double",
                  "show_submit_button": false
                }
              },
              {
                "title": "LL hasTarget",
                "x": 0.0,
                "y": 0.0,
                "width": 128.0,
                "height": 128.0,
                "type": "Boolean Box",
                "properties": {
                  "topic": "/limelight/out//LL hasTarget",
                  "period": 0.06,
                  "data_type": "boolean",
                  "true_color": 4283215696,
                  "false_color": 4294198070,
                  "true_icon": "None",
                  "false_icon": "None"
                }
              },
              {
                "title": "LL_Num_Apriltag",
                "x": 0.0,
                "y": 0.0,
                "width": 128.0,
                "height": 128.0,
                "type": "Text Display",
                "properties": {
                  "topic": "/limelight/out//LL_Num_Apriltag",
                  "period": 0.06,
                  "data_type": "int",
                  "show_submit_button": false
                }
              },
              {
                "title": "Limelight Valid",
                "x": 0.0,
                "y": 0.0,
                "width": 128.0,
                "height": 128.0,
                "type": "Boolean Box",
                "properties": {
                  "topic": "/limelight/out//Limelight Valid",
                  "period": 0.06,
                  "data_type": "boolean",
                  "true_color": 4283215696,
                  "false_color": 4294198070,
                  "true_icon": "None",
                  "false_icon": "None"
                }
              },
              {
                "title": "Limelight X error",
                "x": 0.0,
                "y": 0.0,
                "width": 128.0,
                "height": 128.0,
                "type": "Text Display",
                "properties": {
                  "topic": "/limelight/out//Limelight X error",
                  "period": 0.06,
                  "data_type": "double",
                  "show_submit_button": false
                }
              }
            ]
          }
        ],
        "containers": [
          {
            "title": "robot_orientation_set",
            "x": 1024.0,
            "y": 512.0,
            "width": 384.0,
            "height": 128.0,
            "type": "Text Display",
            "properties": {
              "topic": "/limelight/robot_orientation_set",
              "period": 0.06,
              "data_type": "double[]",
              "show_submit_button": false
            }
          },
          {
            "title": "Auto Chooser",
            "x": 128.0,
            "y": 512.0,
            "width": 256.0,
            "height": 128.0,
            "type": "ComboBox Chooser",
            "properties": {
              "topic": "/SmartDashboard/Auto Chooser",
              "period": 0.06,
              "sort_options": false
            }
          },
          {
            "title": "Robot",
            "x": 1024.0,
            "y": 640.0,
            "width": 384.0,
            "height": 128.0,
            "type": "Text Display",
            "properties": {
              "topic": "/SmartDashboard/Field_vision/Robot",
              "period": 0.06,
              "data_type": "double[]",
              "show_submit_button": false
            }
          },
          {
            "title": "VPE_limelight",
            "x": 1024.0,
            "y": 768.0,
            "width": 384.0,
            "height": 128.0,
            "type": "Text Display",
            "properties": {
              "topic": "/SmartDashboard/Field_vision/VPE_limelight",
              "period": 0.06,
              "data_type": "double[]",
              "show_submit_button": false
            }
          },
          {
            "title": "DriveFieldCentric",
            "x": 768.0,
            "y": 0.0,
            "width": 128.0,
            "height": 128.0,
            "type": "Boolean Box",
            "properties": {
              "topic": "/SmartDashboard/DriveFieldCentric",
              "period": 0.06,
              "data_type": "boolean",
              "true_color": 4283215696,
              "false_color": 4294198070,
              "true_icon": "None",
              "false_icon": "None"
            }
          },
          {
            "title": "DriveRobotCentric",
            "x": 896.0,
            "y": 0.0,
            "width": 128.0,
            "height": 128.0,
            "type": "Boolean Box",
            "properties": {
              "topic": "/SmartDashboard/DriveRobotCentric",
              "period": 0.06,
              "data_type": "boolean",
              "true_color": 4283215696,
              "false_color": 4294198070,
              "true_icon": "None",
              "false_icon": "None"
            }
          }
        ]
      }
    },
    {
      "name": "Autonomous",
      "grid_layout": {
        "layouts": [],
        "containers": []
      }
    }
  ]
}